compare_numbers/__init__.py
compare_numbers/equal.py
compare_numbers/greater.py
compare_numbers/lower.py
compare_numbers/notEqual.py
compare_numbers-0.0.1.dist-info/METADATA
compare_numbers-0.0.1.dist-info/WHEEL
compare_numbers-0.0.1.dist-info/top_level.txt
compare_numbers-0.0.1.dist-info/RECORD
